lgad/__init__.py
lgad/moving_plates.py
lgad/simulation.py
lgad/utility.py
lgad-0.0.1.dist-info/METADATA
lgad-0.0.1.dist-info/RECORD
lgad-0.0.1.dist-info/WHEEL
lgad-0.0.1.dist-info/top_level.txt
